[{"Name":"Place RadTreeView in Dropdown","ExampleInfo":{"Name":"Place RadTreeView in Dropdown","DirectoryName":"TreeViewInDropDown","ExampleFileNames":["TreeViewInDropDown.csproj","app.config","App.xaml","App.xaml.cs","MainWindow.xaml","MainWindow.xaml.cs","MyViewModel.cs","TreeSelectionBridge.cs","TreeViewComboBox.cs","TreeViewDropDownContentManager.cs","TreeViewItemsSourceProvider.cs"]},"GitHubPath":"https://api.github.com/repos/telerik/xaml-sdk/contents/MultiColumnComboBox/TreeViewInDropDown/","Description":"This example demonstrates how to replace the RadGridView element inside the dropdown of the RadMultiColumnComboBox with a RadTreeView.","KeyWords":"Place RadTreeView in Dropdown,  RadTreeView, dropdown"}]